iust_ai/__init__.py
iust_ai/abdi-4031/__init__.py
iust_ai/abdi-4031/decision_tree_submission/__init__.py
iust_ai/abdi-4031/decision_tree_submission/authenticator.py
iust_ai/base_authenticator.py
iust_ai-0.1.1.dist-info/METADATA
iust_ai-0.1.1.dist-info/WHEEL
iust_ai-0.1.1.dist-info/RECORD
